levi/__init__.py
levi-0.3.0.dist-info/LICENSE.md
levi-0.3.0.dist-info/METADATA
levi-0.3.0.dist-info/WHEEL
levi-0.3.0.dist-info/RECORD
