Metadata-Version: 2.1
Name: levi
Version: 0.3.0
Summary: Delta Lake helper methods
Author: Matthew Powers
Author-email: matthewkevinpowers@gmail.com
Requires-Python: >=3.9,<4.0
Classifier: Programming Language :: Python :: 3
Classifier: Programming Language :: Python :: 3.9
Classifier: Programming Language :: Python :: 3.10
Classifier: Programming Language :: Python :: 3.11
Requires-Dist: deltalake[pandas] (>=0.9,<0.10)
